{"matchesPlayedPerYear":{"2008":58,"2009":57,"2010":60,"2011":73,"2012":74,"2013":76,"2014":60,"2015":59,"2016":60,"2017":59,"2018":60,"2019":60},"matchesWonByEachTeam":{"2008":{"Kolkata Knight Riders":6,"Chennai Super Kings":9,"Delhi Daredevils":7,"Royal Challengers Bangalore":4,"Rajasthan Royals":13,"Kings XI Punjab":10,"Deccan Chargers":2,"Mumbai Indians":7},"2009":{"Mumbai Indians":5,"Royal Challengers Bangalore":9,"Delhi Daredevils":10,"Deccan Chargers":9,"Chennai Super Kings":8,"Kolkata Knight Riders":3,"Rajasthan Royals":6,"Kings XI Punjab":7},"2010":{"Kolkata Knight Riders":7,"Mumbai Indians":11,"Delhi Daredevils":7,"Deccan Chargers":8,"Royal Challengers Bangalore":8,"Chennai Super Kings":9,"Rajasthan Royals":6,"Kings XI Punjab":4},"2011":{"Chennai Super Kings":11,"Rajasthan Royals":6,"Royal Challengers Bangalore":10,"Mumbai Indians":10,"Pune Warriors":4,"Kolkata Knight Riders":8,"Kings XI Punjab":7,"Deccan Chargers":6,"Kochi Tuskers Kerala":6,"Delhi Daredevils":4,"":1},"2012":{"Mumbai Indians":10,"Delhi Daredevils":11,"Pune Warriors":4,"Rajasthan Royals":7,"Royal Challengers Bangalore":8,"Chennai Super Kings":10,"Kolkata Knight Riders":12,"Kings XI Punjab":8,"Deccan Chargers":4},"2013":{"Kolkata Knight Riders":6,"Royal Challengers Bangalore":9,"Sunrisers Hyderabad":10,"Rajasthan Royals":11,"Mumbai Indians":13,"Kings XI Punjab":8,"Chennai Super Kings":12,"Pune Warriors":4,"Delhi Daredevils":3},"2014":{"Kolkata Knight Riders":11,"Royal Challengers Bangalore":5,"Kings XI Punjab":12,"Rajasthan Royals":7,"Delhi Daredevils":2,"Chennai Super Kings":10,"Sunrisers Hyderabad":6,"Mumbai Indians":7},"2015":{"Kolkata Knight Riders":7,"Chennai Super Kings":10,"Rajasthan Royals":7,"Royal Challengers Bangalore":8,"Kings XI Punjab":3,"Sunrisers Hyderabad":7,"Delhi Daredevils":5,"Mumbai Indians":10,"":2},"2016":{"Rising Pune Supergiants":5,"Kolkata Knight Riders":8,"Gujarat Lions":9,"Royal Challengers Bangalore":9,"Mumbai Indians":7,"Delhi Daredevils":7,"Kings XI Punjab":4,"Sunrisers Hyderabad":11},"2017":{"Sunrisers Hyderabad":8,"Rising Pune Supergiant":10,"Kolkata Knight Riders":9,"Kings XI Punjab":7,"Royal Challengers Bangalore":3,"Mumbai Indians":12,"Delhi Daredevils":6,"Gujarat Lions":4},"2018":{"Chennai Super Kings":11,"Kings XI Punjab":6,"Kolkata Knight Riders":9,"Sunrisers Hyderabad":10,"Rajasthan Royals":7,"Royal Challengers Bangalore":6,"Delhi Daredevils":5,"Mumbai Indians":6},"2019":{"Chennai Super Kings":10,"Kolkata Knight Riders":6,"Delhi Capitals":10,"Kings XI Punjab":6,"Mumbai Indians":11,"Sunrisers Hyderabad":6,"Rajasthan Royals":5,"Royal Challengers Bangalore":5,"":1}},"extraRunsConcenedByEachTeamIn2016":{"Rising Pune Supergiants":108,"Mumbai Indians":102,"Kolkata Knight Riders":122,"Delhi Daredevils":106,"Gujarat Lions":98,"Kings XI Punjab":100,"Sunrisers Hyderabad":107,"Royal Challengers Bangalore":156},"topTenEconomicalBowlersIn2015":{"RN ten Doeschate":3.6363636363636362,"J Yadav":4.142857142857143,"R Ashwin":5.725,"S Nadeem":5.972222222222222,"Parvez Rasool":6.2,"Z Khan":6.235294117647059,"MC Henriques":6.283524904214559,"V Kohli":6.666666666666667,"MA Starc":6.769911504424778,"Sandeep Sharma":6.970873786407767},"matchesWonByEachTeamVsVenue":{"Rajiv Gandhi International Stadium, Uppal":{"Sunrisers Hyderabad":25,"Rising Pune Supergiant":1,"Mumbai Indians":5,"Delhi Daredevils":4,"Rajasthan Royals":2,"Kings XI Punjab":4,"Royal Challengers Bangalore":2,"Kolkata Knight Riders":5,"Chennai Super Kings":3,"Deccan Chargers":3,"Pune Warriors":1,"Rising Pune Supergiants":1},"Maharashtra Cricket Association Stadium":{"Rising Pune Supergiant":5,"Delhi Daredevils":2,"Kolkata Knight Riders":3,"Rajasthan Royals":1,"Royal Challengers Bangalore":2,"Gujarat Lions":1,"Mumbai Indians":2,"Chennai Super Kings":5},"Saurashtra Cricket Association Stadium":{"Kolkata Knight Riders":1,"Gujarat Lions":3,"Royal Challengers Bangalore":1,"Kings XI Punjab":2,"Mumbai Indians":1,"Sunrisers Hyderabad":1,"Delhi Daredevils":1},"Holkar Cricket Stadium":{"Kings XI Punjab":4,"Mumbai Indians":2,"Kochi Tuskers Kerala":1,"Kolkata Knight Riders":1,"Royal Challengers Bangalore":1},"M Chinnaswamy Stadium":{"Royal Challengers Bangalore":34,"Mumbai Indians":8,"Rising Pune Supergiant":1,"Gujarat Lions":1,"Kings XI Punjab":5,"Kolkata Knight Riders":7,"Rajasthan Royals":4,"Chennai Super Kings":5,"Delhi Daredevils":3,"Deccan Chargers":1,"Sunrisers Hyderabad":2},"Wankhede Stadium":{"Mumbai Indians":42,"Rising Pune Supergiant":2,"Kings XI Punjab":5,"Royal Challengers Bangalore":3,"Rajasthan Royals":4,"Chennai Super Kings":7,"Kochi Tuskers Kerala":1,"Deccan Chargers":1,"Pune Warriors":1,"Delhi Daredevils":2,"Kolkata Knight Riders":1,"Rising Pune Supergiants":1,"Gujarat Lions":1,"Sunrisers Hyderabad":1,"Delhi Capitals":1},"Eden Gardens":{"Kolkata Knight Riders":45,"Gujarat Lions":2,"Rising Pune Supergiant":1,"Mumbai Indians":10,"Chennai Super Kings":5,"Rajasthan Royals":2,"Kings XI Punjab":3,"Kochi Tuskers Kerala":1,"Royal Challengers Bangalore":4,"Delhi Daredevils":1,"Sunrisers Hyderabad":2,"Delhi Capitals":1},"Feroz Shah Kotla":{"Delhi Daredevils":27,"Kolkata Knight Riders":5,"Mumbai Indians":3,"Royal Challengers Bangalore":6,"Chennai Super Kings":5,"Kings XI Punjab":5,"Deccan Chargers":2,"Kochi Tuskers Kerala":1,"Pune Warriors":1,"Rajasthan Royals":4,"Sunrisers Hyderabad":5,"Gujarat Lions":1,"Rising Pune Supergiants":1},"Punjab Cricket Association IS Bindra Stadium, Mohali":{"Sunrisers Hyderabad":2,"Kings XI Punjab":7,"Gujarat Lions":2,"Kolkata Knight Riders":1,"Mumbai Indians":1,"Royal Challengers Bangalore":1},"Green Park":{"Delhi Daredevils":1,"Sunrisers Hyderabad":1,"Gujarat Lions":2},"Punjab Cricket Association Stadium, Mohali":{"Chennai Super Kings":3,"Kings XI Punjab":18,"Delhi Daredevils":1,"Rajasthan Royals":3,"Kolkata Knight Riders":2,"Royal Challengers Bangalore":2,"Pune Warriors":1,"Mumbai Indians":3,"Sunrisers Hyderabad":2},"Sawai Mansingh Stadium":{"Rajasthan Royals":32,"Mumbai Indians":2,"Royal Challengers Bangalore":3,"Kolkata Knight Riders":3,"Chennai Super Kings":3,"Delhi Daredevils":1,"Sunrisers Hyderabad":1,"Kings XI Punjab":1,"Delhi Capitals":1},"MA Chidambaram Stadium, Chepauk":{"Chennai Super Kings":34,"Delhi Daredevils":2,"Deccan Chargers":2,"Royal Challengers Bangalore":2,"Rajasthan Royals":1,"Kings XI Punjab":2,"Mumbai Indians":3,"Kolkata Knight Riders":2,"Pune Warriors":1},"Dr DY Patil Sports Academy":{"Deccan Chargers":2,"Mumbai Indians":5,"Rajasthan Royals":1,"Kolkata Knight Riders":2,"Chennai Super Kings":3,"Royal Challengers Bangalore":1,"Pune Warriors":2,"Delhi Daredevils":1},"Newlands":{"Mumbai Indians":1,"Royal Challengers Bangalore":1,"Delhi Daredevils":1,"Deccan Chargers":2,"Rajasthan Royals":1,"Kings XI Punjab":1},"St George's Park":{"Chennai Super Kings":2,"Delhi Daredevils":1,"Mumbai Indians":2,"Rajasthan Royals":1,"Kings XI Punjab":1},"Kingsmead":{"Kolkata Knight Riders":2,"Delhi Daredevils":3,"Kings XI Punjab":2,"Deccan Chargers":2,"Royal Challengers Bangalore":3,"Rajasthan Royals":2,"Chennai Super Kings":1},"SuperSport Park":{"Rajasthan Royals":2,"Delhi Daredevils":2,"Chennai Super Kings":2,"Deccan Chargers":2,"Royal Challengers Bangalore":2,"Mumbai Indians":1,"Kolkata Knight Riders":1},"Buffalo Park":{"Mumbai Indians":1,"Chennai Super Kings":1,"Delhi Daredevils":1},"New Wanderers Stadium":{"Chennai Super Kings":1,"Royal Challengers Bangalore":3,"Delhi Daredevils":1,"Deccan Chargers":2,"Kings XI Punjab":1},"De Beers Diamond Oval":{"Kings XI Punjab":1,"Chennai Super Kings":1,"Deccan Chargers":1},"OUTsurance Oval":{"Kings XI Punjab":1,"Delhi Daredevils":1},"Brabourne Stadium":{"Mumbai Indians":6,"Royal Challengers Bangalore":1,"Chennai Super Kings":1,"Rajasthan Royals":2,"Sunrisers Hyderabad":1},"Sardar Patel Stadium, Motera":{"Delhi Daredevils":1,"Rajasthan Royals":7,"Sunrisers Hyderabad":1,"Mumbai Indians":1,"Kings XI Punjab":1,"Royal Challengers Bangalore":1},"Barabati Stadium":{"Deccan Chargers":3,"Kolkata Knight Riders":3,"Kings XI Punjab":1},"Vidarbha Cricket Association Stadium, Jamtha":{"Rajasthan Royals":1,"Deccan Chargers":2},"Himachal Pradesh Cricket Association Stadium":{"Deccan Chargers":2,"Chennai Super Kings":1,"Kings XI Punjab":5,"Delhi Daredevils":1},"Nehru Stadium":{"Royal Challengers Bangalore":1,"Kochi Tuskers Kerala":2,"Deccan Chargers":1,"Delhi Daredevils":1},"Dr. Y.S. Rajasekhara Reddy ACA-VDCA Cricket Stadium":{"Chennai Super Kings":1,"Mumbai Indians":2,"Rajasthan Royals":1,"Delhi Daredevils":1,"Sunrisers Hyderabad":3,"Kings XI Punjab":1,"Rising Pune Supergiants":2},"Subrata Roy Sahara Stadium":{"Pune Warriors":4,"Delhi Daredevils":1,"Deccan Chargers":1,"Mumbai Indians":2,"Rajasthan Royals":1,"Royal Challengers Bangalore":2,"Kolkata Knight Riders":3,"Kings XI Punjab":1,"Sunrisers Hyderabad":1,"Chennai Super Kings":1},"Shaheed Veer Narayan Singh International Stadium":{"Delhi Daredevils":4,"Sunrisers Hyderabad":1,"Royal Challengers Bangalore":1},"JSCA International Stadium Complex":{"Kolkata Knight Riders":1,"Pune Warriors":1,"Chennai Super Kings":3,"Royal Challengers Bangalore":1,"Sunrisers Hyderabad":1},"Sheikh Zayed Stadium":{"Kolkata Knight Riders":1,"Kings XI Punjab":2,"Rajasthan Royals":3,"Chennai Super Kings":1},"Sharjah Cricket Stadium":{"Royal Challengers Bangalore":1,"Kings XI Punjab":2,"Kolkata Knight Riders":1,"Delhi Daredevils":1,"Chennai Super Kings":1},"Dubai International Cricket Stadium":{"Royal Challengers Bangalore":1,"Delhi Daredevils":1,"Chennai Super Kings":2,"Sunrisers Hyderabad":2,"Kings XI Punjab":1},"M. A. Chidambaram Stadium":{"Chennai Super Kings":6,"Mumbai Indians":2},"Feroz Shah Kotla Ground":{"Chennai Super Kings":1,"Delhi Capitals":4,"Sunrisers Hyderabad":1,"Mumbai Indians":1},"M. Chinnaswamy Stadium":{"Mumbai Indians":1,"Kolkata Knight Riders":1,"Delhi Capitals":1,"Royal Challengers Bangalore":3},"Rajiv Gandhi Intl. Cricket Stadium":{"Sunrisers Hyderabad":5,"Mumbai Indians":2,"Delhi Capitals":1},"IS Bindra Stadium":{"Kings XI Punjab":5,"Royal Challengers Bangalore":1,"Kolkata Knight Riders":1},"ACA-VDCA Stadium":{"Delhi Capitals":1,"Chennai Super Kings":1}}}